appver/__init__.py
appver/__main__.py
appver/_version.py
appver/appver.py
appver-0.1.1.dist-info/LICENSE
appver-0.1.1.dist-info/METADATA
appver-0.1.1.dist-info/WHEEL
appver-0.1.1.dist-info/top_level.txt
appver-0.1.1.dist-info/RECORD
