Metadata-Version: 2.1
Name: appver
Version: 0.1.1
Summary: simple cli utility for managing version-file
Author-email: inerject <kumbalup@gmail.com>
Project-URL: Homepage, https://github.com/inerject/appver
Classifier: Programming Language :: Python :: 3
Classifier: License :: OSI Approved :: MIT License
Classifier: Operating System :: OS Independent
Requires-Python: >=3.8
License-File: LICENSE
